vicon/__init__.py
vicon/run_pipeline.py
vicon/alignment/__init__.py
vicon/alignment/ref_align.py
vicon/dereplication/__init__.py
vicon/dereplication/derep.py
vicon/io/__init__.py
vicon/io/fasta.py
vicon/io/wig.py
vicon/processing/__init__.py
vicon/processing/coverage_analysis.py
vicon/processing/kmer_analysis.py
vicon/processing/sample_processing.py
vicon/processing/sliding_window.py
vicon/scripts/ViralMSA.py
vicon/utils/__init__.py
vicon/utils/helpers.py
vicon/utils/year_extraction.py
vicon/visualization/__init__.py
vicon/visualization/plots.py
vicon-1.0.4.data/data/bin/ViralMSA.py
vicon-1.0.4.dist-info/licenses/LICENSE
vicon-1.0.4.dist-info/METADATA
vicon-1.0.4.dist-info/WHEEL
vicon-1.0.4.dist-info/entry_points.txt
vicon-1.0.4.dist-info/top_level.txt
vicon-1.0.4.dist-info/RECORD
