Metadata-Version: 2.4
Name: vicon
Version: 1.0.4
Summary: VICON - Viral Conserved Sequence Extraction Toolkit
Author-email: Ehsan Karimiara <e.karimiara@gmail.com>
License-Expression: MIT
Project-URL: Homepage, https://github.com/EhsanKA/vicon
Project-URL: Documentation, https://github.com/EhsanKA/vicon#readme
Project-URL: Repository, https://github.com/EhsanKA/vicon.git
Project-URL: Issues, https://github.com/EhsanKA/vicon/issues
Classifier: Development Status :: 4 - Beta
Classifier: Intended Audience :: Science/Research
Classifier: Programming Language :: Python :: 3
Classifier: Programming Language :: Python :: 3.7
Classifier: Programming Language :: Python :: 3.8
Classifier: Programming Language :: Python :: 3.9
Classifier: Programming Language :: Python :: 3.10
Classifier: Programming Language :: Python :: 3.11
Classifier: Programming Language :: Python :: 3.12
Classifier: Programming Language :: Python :: 3.13
Classifier: Topic :: Scientific/Engineering :: Bio-Informatics
Requires-Python: >=3.7
License-File: LICENSE
Requires-Dist: numpy>=1.24
Requires-Dist: pandas
Requires-Dist: matplotlib
Requires-Dist: biopython
Requires-Dist: pyyaml
Dynamic: license-file
